django_ssh_deployer/__init__.py
django_ssh_deployer/management/__init__.py
django_ssh_deployer/management/commands/__init__.py
django_ssh_deployer/management/commands/deploy.py
django_ssh_deployer-1.0.0.dist-info/LICENSE
django_ssh_deployer-1.0.0.dist-info/METADATA
django_ssh_deployer-1.0.0.dist-info/WHEEL
django_ssh_deployer-1.0.0.dist-info/top_level.txt
django_ssh_deployer-1.0.0.dist-info/RECORD
