Metadata-Version: 2.1
Name: django-ssh-deployer
Version: 1.0.0
Summary: Deploys Django websites via management commands over SSH via Paramiko.
Author-email: Tim Allen <flipper@peregrinesalon.com>
License: BSD-3-Clause
Project-URL: Homepage, https://github.com/FlipperPA/django-ssh-deployer
Project-URL: Repository, https://github.com/FlipperPA/django-ssh-deployer
Project-URL: Documentation, https://github.com/FlipperPA/django-ssh-deployer
Keywords: standard and poors
Classifier: Development Status :: 5 - Production/Stable
Classifier: Environment :: Web Environment
Classifier: Intended Audience :: Developers
Classifier: License :: OSI Approved :: BSD License
Classifier: Operating System :: OS Independent
Classifier: Programming Language :: Python :: 3
Classifier: Programming Language :: Python :: 3.8
Classifier: Programming Language :: Python :: 3.9
Classifier: Programming Language :: Python :: 3.10
Classifier: Programming Language :: Python :: 3.11
Classifier: Programming Language :: Python :: 3.12
Classifier: Framework :: Django
Classifier: Topic :: Internet :: WWW/HTTP
Classifier: Topic :: Internet :: WWW/HTTP :: Dynamic Content
Requires-Python: >=3.6
License-File: LICENSE
Requires-Dist: Django
Requires-Dist: paramiko
